pyminesweeper/__init__.py
pyminesweeper/minesweeperagent.py
pyminesweeper/minesweepermap.py
pyminesweeper/minesweeperui.py
python_minesweeper-0.1.1.dist-info/LICENSE.md
python_minesweeper-0.1.1.dist-info/METADATA
python_minesweeper-0.1.1.dist-info/WHEEL
python_minesweeper-0.1.1.dist-info/top_level.txt
python_minesweeper-0.1.1.dist-info/RECORD
