Metadata-Version: 2.1
Name: python-minesweeper
Version: 0.1.1
Summary: Minesweeper module for Python
Home-page: https://github.com/BaibhaVatsa/minesweeper
Author: Baibhav Vatsa
Author-email: baibhavvatsa@gmail.com
License: UNKNOWN
Platform: UNKNOWN
Classifier: Programming Language :: Python :: 3
Classifier: License :: OSI Approved :: MIT License
Classifier: Operating System :: OS Independent
